{"generated": "2026-07-20T17:13+00:00", "season": 2026, "lg_hrpa": 0.02148, "players": {"alika williams": {"marcel": 0.00706, "age": 27, "seasons": 2, "cur_hr": 2, "cur_pa": 92}, "brent rooker": {"marcel": 0.05053, "age": 32, "seasons": 4, "cur_hr": 10, "cur_pa": 203}, "brian serven": {"marcel": 0.02058, "age": 31, "seasons": 2, "cur_hr": 0, "cur_pa": 4}, "carlos cortes": {"marcel": 0.03089, "age": 29, "seasons": 1, "cur_hr": 7, "cur_pa": 240}, "colby thomas": {"marcel": 0.03596, "age": 25, "seasons": 1, "cur_hr": 4, "cur_pa": 107}, "darell hernaiz": {"marcel": 0.01232, "age": 25, "seasons": 2, "cur_hr": 1, "cur_pa": 134}, "denzel clarke": {"marcel": 0.02023, "age": 26, "seasons": 1, "cur_hr": 0, "cur_pa": 60}, "donovan walton": {"marcel": 0.01787, "age": 32, "seasons": 3, "cur_hr": 3, "cur_pa": 97}, "henry bolte": {"marcel": 0.02148, "age": 23, "seasons": 0, "cur_hr": 3, "cur_pa": 209}, "jacob wilson": {"marcel": 0.02212, "age": 24, "seasons": 2, "cur_hr": 5, "cur_pa": 251}, "jeff mcneil": {"marcel": 0.02207, "age": 34, "seasons": 8, "cur_hr": 3, "cur_pa": 300}, "jonah heim": {"marcel": 0.02795, "age": 31, "seasons": 5, "cur_hr": 1, "cur_pa": 45}, "joshua kuroda-grauer": {"marcel": 0.02148, "age": 23, "seasons": 0, "cur_hr": 0, "cur_pa": 59}, "lawrence butler": {"marcel": 0.03776, "age": 26, "seasons": 3, "cur_hr": 5, "cur_pa": 284}, "max muncy": {"marcel": 0.05074, "age": 36, "seasons": 10, "cur_hr": 18, "cur_pa": 348}, "nick kurtz": {"marcel": 0.0671, "age": 23, "seasons": 1, "cur_hr": 20, "cur_pa": 412}, "shea langeliers": {"marcel": 0.05219, "age": 29, "seasons": 4, "cur_hr": 22, "cur_pa": 399}, "tommy white": {"marcel": 0.02148, "age": 23, "seasons": 0, "cur_hr": 0, "cur_pa": 7}, "tyler soderstrom": {"marcel": 0.03804, "age": 25, "seasons": 3, "cur_hr": 16, "cur_pa": 360}, "zack gelof": {"marcel": 0.03265, "age": 27, "seasons": 3, "cur_hr": 11, "cur_pa": 247}, "billy cook": {"marcel": 0.02148, "age": 27, "seasons": 0, "cur_hr": 0, "cur_pa": 39}, "brandon lowe": {"marcel": 0.04982, "age": 32, "seasons": 8, "cur_hr": 21, "cur_pa": 410}, "bryan reynolds": {"marcel": 0.03052, "age": 31, "seasons": 7, "cur_hr": 14, "cur_pa": 435}, "endy rodriguez": {"marcel": 0.01408, "age": 26, "seasons": 2, "cur_hr": 5, "cur_pa": 122}, "esmerlyn valdez": {"marcel": 0.02148, "age": 22, "seasons": 0, "cur_hr": 12, "cur_pa": 118}, "henry davis": {"marcel": 0.02262, "age": 27, "seasons": 3, "cur_hr": 8, "cur_pa": 196}, "jack brannigan": {"marcel": 0.02148, "age": 25, "seasons": 0, "cur_hr": 0, "cur_pa": 1}, "jacob gonzalez": {"marcel": 0.02148, "age": 24, "seasons": 0, "cur_hr": 2, "cur_pa": 97}, "jake mangum": {"marcel": 0.00972, "age": 30, "seasons": 1, "cur_hr": 2, "cur_pa": 268}, "jared triolo": {"marcel": 0.01901, "age": 28, "seasons": 3, "cur_hr": 1, "cur_pa": 223}, "jhostynxon garcia": {"marcel": 0.02148, "age": 24, "seasons": 0, "cur_hr": 0, "cur_pa": 37}, "konnor griffin": {"marcel": 0.02148, "age": 20, "seasons": 0, "cur_hr": 5, "cur_pa": 247}, "marcell ozuna": {"marcel": 0.04835, "age": 36, "seasons": 13, "cur_hr": 8, "cur_pa": 254}, "nick gonzales": {"marcel": 0.01569, "age": 27, "seasons": 3, "cur_hr": 5, "cur_pa": 386}, "nick yorke": {"marcel": 0.01885, "age": 24, "seasons": 1, "cur_hr": 1, "cur_pa": 86}, "oneil cruz": {"marcel": 0.03711, "age": 28, "seasons": 3, "cur_hr": 14, "cur_pa": 283}, "rafael flores jr": {"marcel": 0.02148, "age": 26, "seasons": 0, "cur_hr": 1, "cur_pa": 16}, "ryan ohearn": {"marcel": 0.03044, "age": 33, "seasons": 10, "cur_hr": 16, "cur_pa": 352}, "spencer horwitz": {"marcel": 0.02796, "age": 29, "seasons": 2, "cur_hr": 10, "cur_pa": 295}, "tyler callihan": {"marcel": 0.02148, "age": 26, "seasons": 0, "cur_hr": 3, "cur_pa": 93}, "blake hunt": {"marcel": 0.02148, "age": 28, "seasons": 0, "cur_hr": 0, "cur_pa": 3}, "fernando tatis jr": {"marcel": 0.03941, "age": 27, "seasons": 6, "cur_hr": 7, "cur_pa": 430}, "freddy fermin": {"marcel": 0.01521, "age": 31, "seasons": 5, "cur_hr": 3, "cur_pa": 167}, "gavin sheets": {"marcel": 0.02808, "age": 30, "seasons": 5, "cur_hr": 14, "cur_pa": 331}, "jackson merrill": {"marcel": 0.03674, "age": 23, "seasons": 2, "cur_hr": 12, "cur_pa": 407}, "jake cronenworth": {"marcel": 0.02235, "age": 32, "seasons": 6, "cur_hr": 3, "cur_pa": 170}, "jase bowen": {"marcel": 0.02148, "age": 26, "seasons": 0, "cur_hr": 0, "cur_pa": 50}, "luis campusano": {"marcel": 0.02908, "age": 28, "seasons": 3, "cur_hr": 4, "cur_pa": 87}, "luis rengifo": {"marcel": 0.0222, "age": 29, "seasons": 7, "cur_hr": 0, "cur_pa": 209}, "manny machado": {"marcel": 0.04216, "age": 34, "seasons": 16, "cur_hr": 19, "cur_pa": 404}, "mason mccoy": {"marcel": 0.0136, "age": 31, "seasons": 1, "cur_hr": 0, "cur_pa": 0}, "miguel andujar": {"marcel": 0.0279, "age": 31, "seasons": 10, "cur_hr": 5, "cur_pa": 254}, "ramon laureano": {"marcel": 0.04637, "age": 32, "seasons": 14, "cur_hr": 7, "cur_pa": 206}, "rodolfo duran": {"marcel": 0.02148, "age": 28, "seasons": 0, "cur_hr": 3, "cur_pa": 91}, "samad taylor": {"marcel": 0.01279, "age": 28, "seasons": 1, "cur_hr": 1, "cur_pa": 102}, "sung-mun song": {"marcel": 0.02148, "age": 30, "seasons": 0, "cur_hr": 1, "cur_pa": 102}, "ty france": {"marcel": 0.01493, "age": 32, "seasons": 13, "cur_hr": 14, "cur_pa": 243}, "will wagner": {"marcel": 0.00776, "age": 28, "seasons": 3, "cur_hr": 0, "cur_pa": 45}, "xander bogaerts": {"marcel": 0.02314, "age": 34, "seasons": 13, "cur_hr": 9, "cur_pa": 377}, "brendan donovan": {"marcel": 0.02204, "age": 29, "seasons": 4, "cur_hr": 3, "cur_pa": 101}, "brennen davis": {"marcel": 0.02148, "age": 27, "seasons": 0, "cur_hr": 0, "cur_pa": 0}, "buddy kennedy": {"marcel": 0.01632, "age": 28, "seasons": 1, "cur_hr": 0, "cur_pa": 8}, "cal raleigh": {"marcel": 0.06541, "age": 30, "seasons": 5, "cur_hr": 9, "cur_pa": 292}, "cole young": {"marcel": 0.01784, "age": 23, "seasons": 1, "cur_hr": 13, "cur_pa": 395}, "colt emerson": {"marcel": 0.02148, "age": 21, "seasons": 0, "cur_hr": 7, "cur_pa": 171}, "connor joe": {"marcel": 0.01496, "age": 34, "seasons": 6, "cur_hr": 1, "cur_pa": 45}, "dominic canzone": {"marcel": 0.03775, "age": 29, "seasons": 4, "cur_hr": 15, "cur_pa": 262}, "jp crawford": {"marcel": 0.02174, "age": 31, "seasons": 9, "cur_hr": 10, "cur_pa": 349}, "jhonny pereda": {"marcel": 0.01203, "age": 30, "seasons": 1, "cur_hr": 2, "cur_pa": 68}, "josh naylor": {"marcel": 0.03181, "age": 29, "seasons": 10, "cur_hr": 8, "cur_pa": 400}, "julio rodriguez": {"marcel": 0.04106, "age": 26, "seasons": 4, "cur_hr": 14, "cur_pa": 388}, "leo rivas": {"marcel": 0.01461, "age": 29, "seasons": 2, "cur_hr": 0, "cur_pa": 120}, "luke raley": {"marcel": 0.03801, "age": 32, "seasons": 5, "cur_hr": 15, "cur_pa": 267}, "mitch garver": {"marcel": 0.03642, "age": 35, "seasons": 9, "cur_hr": 4, "cur_pa": 135}, "patrick wisdom": {"marcel": 0.05216, "age": 35, "seasons": 5, "cur_hr": 1, "cur_pa": 44}, "randy arozarena": {"marcel": 0.03443, "age": 31, "seasons": 8, "cur_hr": 11, "cur_pa": 391}, "rob refsnyder": {"marcel": 0.02905, "age": 35, "seasons": 9, "cur_hr": 3, "cur_pa": 119}, "ryan bliss": {"marcel": 0.02455, "age": 27, "seasons": 1, "cur_hr": 0, "cur_pa": 10}, "victor robles": {"marcel": 0.01426, "age": 29, "seasons": 9, "cur_hr": 0, "cur_pa": 109}, "weston wilson": {"marcel": 0.03148, "age": 32, "seasons": 2, "cur_hr": 1, "cur_pa": 46}, "will wilson": {"marcel": 0.01131, "age": 28, "seasons": 1, "cur_hr": 1, "cur_pa": 6}, "bryce eldridge": {"marcel": 0.02148, "age": 22, "seasons": 0, "cur_hr": 10, "cur_pa": 231}, "casey schmitt": {"marcel": 0.03178, "age": 27, "seasons": 3, "cur_hr": 19, "cur_pa": 384}, "christian koss": {"marcel": 0.0178, "age": 28, "seasons": 1, "cur_hr": 0, "cur_pa": 20}, "daniel susac": {"marcel": 0.02148, "age": 25, "seasons": 0, "cur_hr": 0, "cur_pa": 119}, "drew cavanaugh": {"marcel": 0.02148, "age": 24, "seasons": 0, "cur_hr": 0, "cur_pa": 45}, "drew gilbert": {"marcel": 0.02507, "age": 26, "seasons": 1, "cur_hr": 4, "cur_pa": 225}, "grant mccray": {"marcel": 0.03164, "age": 26, "seasons": 1, "cur_hr": 0, "cur_pa": 4}, "harrison bader": {"marcel": 0.03288, "age": 32, "seasons": 13, "cur_hr": 5, "cur_pa": 111}, "heliot ramos": {"marcel": 0.0337, "age": 27, "seasons": 3, "cur_hr": 8, "cur_pa": 248}, "jesus rodriguez": {"marcel": 0.02148, "age": 24, "seasons": 0, "cur_hr": 2, "cur_pa": 46}, "jonah cox": {"marcel": 0.02148, "age": 25, "seasons": 0, "cur_hr": 1, "cur_pa": 29}, "jung hoo lee": {"marcel": 0.01398, "age": 28, "seasons": 2, "cur_hr": 5, "cur_pa": 364}, "luis arraez": {"marcel": 0.01022, "age": 29, "seasons": 9, "cur_hr": 4, "cur_pa": 416}, "matt chapman": {"marcel": 0.03637, "age": 33, "seasons": 9, "cur_hr": 7, "cur_pa": 352}, "rafael devers": {"marcel": 0.04599, "age": 30, "seasons": 11, "cur_hr": 20, "cur_pa": 421}, "victor bericoto": {"marcel": 0.02148, "age": 25, "seasons": 0, "cur_hr": 4, "cur_pa": 59}, "willy adames": {"marcel": 0.04195, "age": 31, "seasons": 10, "cur_hr": 17, "cur_pa": 397}, "alec burleson": {"marcel": 0.0317, "age": 28, "seasons": 4, "cur_hr": 15, "cur_pa": 412}, "blaze jordan": {"marcel": 0.02148, "age": 24, "seasons": 0, "cur_hr": 1, "cur_pa": 88}, "bryan torres": {"marcel": 0.02148, "age": 29, "seasons": 0, "cur_hr": 4, "cur_pa": 74}, "cesar prieto": {"marcel": 0.02148, "age": 27, "seasons": 0, "cur_hr": 0, "cur_pa": 17}, "ivan herrera": {"marcel": 0.03384, "age": 26, "seasons": 2, "cur_hr": 11, "cur_pa": 439}, "jj wetherholt": {"marcel": 0.02148, "age": 24, "seasons": 0, "cur_hr": 14, "cur_pa": 423}, "jimmy crooks": {"marcel": 0.02148, "age": 25, "seasons": 0, "cur_hr": 3, "cur_pa": 75}, "jordan walker": {"marcel": 0.02447, "age": 24, "seasons": 3, "cur_hr": 22, "cur_pa": 410}, "jose fermin": {"marcel": 0.01105, "age": 27, "seasons": 3, "cur_hr": 4, "cur_pa": 186}, "joshua baez": {"marcel": 0.02148, "age": 23, "seasons": 0, "cur_hr": 0, "cur_pa": 0}, "lars nootbaar": {"marcel": 0.02538, "age": 29, "seasons": 5, "cur_hr": 3, "cur_pa": 134}, "leo bernal": {"marcel": 0.02148, "age": 22, "seasons": 0, "cur_hr": 0, "cur_pa": 0}, "masyn winn": {"marcel": 0.02039, "age": 24, "seasons": 3, "cur_hr": 4, "cur_pa": 370}, "nathan church": {"marcel": 0.01942, "age": 26, "seasons": 1, "cur_hr": 8, "cur_pa": 265}, "nelson velazquez": {"marcel": 0.05839, "age": 28, "seasons": 4, "cur_hr": 4, "cur_pa": 68}, "nolan gorman": {"marcel": 0.04435, "age": 26, "seasons": 4, "cur_hr": 7, "cur_pa": 229}, "pedro pages": {"marcel": 0.0285, "age": 28, "seasons": 2, "cur_hr": 4, "cur_pa": 162}, "ramon urias": {"marcel": 0.02709, "age": 32, "seasons": 7, "cur_hr": 2, "cur_pa": 68}, "thomas saggese": {"marcel": 0.0116, "age": 24, "seasons": 2, "cur_hr": 1, "cur_pa": 82}, "victor scott ii": {"marcel": 0.01297, "age": 25, "seasons": 2, "cur_hr": 2, "cur_pa": 184}, "ben williamson": {"marcel": 0.00811, "age": 26, "seasons": 1, "cur_hr": 2, "cur_pa": 230}, "carson williams": {"marcel": 0.03595, "age": 23, "seasons": 1, "cur_hr": 0, "cur_pa": 33}, "cedric mullins": {"marcel": 0.03336, "age": 32, "seasons": 10, "cur_hr": 11, "cur_pa": 327}, "chandler simpson": {"marcel": 0.00404, "age": 26, "seasons": 1, "cur_hr": 0, "cur_pa": 366}, "gavin lux": {"marcel": 0.0146, "age": 29, "seasons": 6, "cur_hr": 0, "cur_pa": 0}, "hunter feduccia": {"marcel": 0.007, "age": 29, "seasons": 2, "cur_hr": 2, "cur_pa": 144}, "jacob melton": {"marcel": 0.01228, "age": 26, "seasons": 1, "cur_hr": 0, "cur_pa": 0}, "jadher areinamo": {"marcel": 0.02148, "age": 23, "seasons": 0, "cur_hr": 0, "cur_pa": 0}, "jake fraley": {"marcel": 0.02284, "age": 31, "seasons": 6, "cur_hr": 2, "cur_pa": 90}, "jonathan aranda": {"marcel": 0.03207, "age": 28, "seasons": 4, "cur_hr": 14, "cur_pa": 420}, "jonny deluca": {"marcel": 0.01534, "age": 28, "seasons": 2, "cur_hr": 6, "cur_pa": 189}, "junior caminero": {"marcel": 0.06034, "age": 23, "seasons": 2, "cur_hr": 29, "cur_pa": 428}, "nick fortes": {"marcel": 0.02033, "age": 30, "seasons": 6, "cur_hr": 2, "cur_pa": 230}, "oliver dunn": {"marcel": 0.01543, "age": 29, "seasons": 1, "cur_hr": 0, "cur_pa": 12}, "richie palacios": {"marcel": 0.0209, "age": 29, "seasons": 3, "cur_hr": 3, "cur_pa": 236}, "ryan vilade": {"marcel": 0.02148, "age": 27, "seasons": 0, "cur_hr": 7, "cur_pa": 167}, "taylor walls": {"marcel": 0.01396, "age": 30, "seasons": 5, "cur_hr": 0, "cur_pa": 277}, "victor mesa jr": {"marcel": 0.02148, "age": 25, "seasons": 0, "cur_hr": 7, "cur_pa": 112}, "yandy diaz": {"marcel": 0.03161, "age": 35, "seasons": 9, "cur_hr": 13, "cur_pa": 412}, "alejandro osuna": {"marcel": 0.01548, "age": 24, "seasons": 1, "cur_hr": 1, "cur_pa": 191}, "brandon nimmo": {"marcel": 0.03518, "age": 33, "seasons": 10, "cur_hr": 9, "cur_pa": 397}, "cam cauley": {"marcel": 0.02148, "age": 23, "seasons": 0, "cur_hr": 0, "cur_pa": 28}, "cody freeman": {"marcel": 0.02385, "age": 25, "seasons": 1, "cur_hr": 0, "cur_pa": 18}, "corey seager": {"marcel": 0.05181, "age": 32, "seasons": 11, "cur_hr": 10, "cur_pa": 219}, "danny jansen": {"marcel": 0.0388, "age": 31, "seasons": 12, "cur_hr": 3, "cur_pa": 142}, "elias diaz": {"marcel": 0.02147, "age": 36, "seasons": 10, "cur_hr": 2, "cur_pa": 23}, "evan carter": {"marcel": 0.02967, "age": 24, "seasons": 3, "cur_hr": 8, "cur_pa": 274}, "ezequiel duran": {"marcel": 0.01599, "age": 27, "seasons": 4, "cur_hr": 10, "cur_pa": 337}, "jake burger": {"marcel": 0.05007, "age": 30, "seasons": 6, "cur_hr": 16, "cur_pa": 386}, "joc pederson": {"marcel": 0.03757, "age": 34, "seasons": 13, "cur_hr": 16, "cur_pa": 302}, "josh jung": {"marcel": 0.03363, "age": 28, "seasons": 4, "cur_hr": 9, "cur_pa": 390}, "josh smith": {"marcel": 0.02048, "age": 29, "seasons": 4, "cur_hr": 1, "cur_pa": 138}, "justin foscue": {"marcel": 0.02148, "age": 27, "seasons": 0, "cur_hr": 7, "cur_pa": 124}, "kyle higashioka": {"marcel": 0.04087, "age": 36, "seasons": 7, "cur_hr": 7, "cur_pa": 185}, "michael helman": {"marcel": 0.03394, "age": 30, "seasons": 1, "cur_hr": 1, "cur_pa": 35}, "nicky lopez": {"marcel": 0.00482, "age": 31, "seasons": 8, "cur_hr": 0, "cur_pa": 5}, "wyatt langford": {"marcel": 0.03393, "age": 25, "seasons": 2, "cur_hr": 10, "cur_pa": 204}, "addison barger": {"marcel": 0.03733, "age": 27, "seasons": 2, "cur_hr": 0, "cur_pa": 28}, "alejandro kirk": {"marcel": 0.02236, "age": 28, "seasons": 5, "cur_hr": 2, "cur_pa": 107}, "andres gimenez": {"marcel": 0.01891, "age": 28, "seasons": 6, "cur_hr": 7, "cur_pa": 318}, "anthony santander": {"marcel": 0.04837, "age": 32, "seasons": 8, "cur_hr": 0, "cur_pa": 0}, "brandon valenzuela": {"marcel": 0.02148, "age": 26, "seasons": 0, "cur_hr": 8, "cur_pa": 191}, "charles mcadoo": {"marcel": 0.02148, "age": 24, "seasons": 0, "cur_hr": 1, "cur_pa": 25}, "daulton varsho": {"marcel": 0.04331, "age": 30, "seasons": 6, "cur_hr": 7, "cur_pa": 318}, "davis schneider": {"marcel": 0.03739, "age": 27, "seasons": 3, "cur_hr": 3, "cur_pa": 118}, "ernie clement": {"marcel": 0.01968, "age": 30, "seasons": 6, "cur_hr": 8, "cur_pa": 387}, "george springer": {"marcel": 0.03833, "age": 37, "seasons": 12, "cur_hr": 10, "cur_pa": 301}, "jesus sanchez": {"marcel": 0.02768, "age": 29, "seasons": 7, "cur_hr": 7, "cur_pa": 234}, "jonatan clase": {"marcel": 0.01916, "age": 24, "seasons": 2, "cur_hr": 2, "cur_pa": 25}, "kazuma okamoto": {"marcel": 0.02148, "age": 30, "seasons": 0, "cur_hr": 22, "cur_pa": 395}, "lenyn sosa": {"marcel": 0.03348, "age": 26, "seasons": 3, "cur_hr": 0, "cur_pa": 33}, "luis urias": {"marcel": 0.02506, "age": 29, "seasons": 10, "cur_hr": 2, "cur_pa": 32}, "myles straw": {"marcel": 0.00555, "age": 32, "seasons": 8, "cur_hr": 3, "cur_pa": 169}, "nathan lukes": {"marcel": 0.02427, "age": 32, "seasons": 2, "cur_hr": 5, "cur_pa": 227}, "sean keys": {"marcel": 0.02148, "age": 23, "seasons": 0, "cur_hr": 1, "cur_pa": 35}, "vladimir guerrero jr": {"marcel": 0.03769, "age": 27, "seasons": 7, "cur_hr": 6, "cur_pa": 399}, "willie maciver": {"marcel": 0.02432, "age": 30, "seasons": 1, "cur_hr": 0, "cur_pa": 0}, "yohendrick pinango": {"marcel": 0.02148, "age": 24, "seasons": 0, "cur_hr": 5, "cur_pa": 160}, "alan roden": {"marcel": 0.01406, "age": 27, "seasons": 2, "cur_hr": 0, "cur_pa": 21}, "alex jackson": {"marcel": 0.02875, "age": 31, "seasons": 4, "cur_hr": 1, "cur_pa": 57}, "austin martin": {"marcel": 0.00788, "age": 27, "seasons": 2, "cur_hr": 2, "cur_pa": 281}, "brooks lee": {"marcel": 0.02718, "age": 25, "seasons": 2, "cur_hr": 14, "cur_pa": 385}, "byron buxton": {"marcel": 0.05303, "age": 33, "seasons": 11, "cur_hr": 25, "cur_pa": 335}, "emmanuel rodriguez": {"marcel": 0.02148, "age": 23, "seasons": 0, "cur_hr": 0, "cur_pa": 0}, "gabriel gonzalez": {"marcel": 0.02148, "age": 22, "seasons": 0, "cur_hr": 0, "cur_pa": 4}, "hendry mendez": {"marcel": 0.02148, "age": 23, "seasons": 0, "cur_hr": 0, "cur_pa": 0}, "josh bell": {"marcel": 0.03505, "age": 34, "seasons": 16, "cur_hr": 13, "cur_pa": 387}, "kody clemens": {"marcel": 0.04603, "age": 30, "seasons": 5, "cur_hr": 18, "cur_pa": 342}, "kyler fedko": {"marcel": 0.02148, "age": 27, "seasons": 0, "cur_hr": 0, "cur_pa": 19}, "luke keaschall": {"marcel": 0.02063, "age": 24, "seasons": 1, "cur_hr": 4, "cur_pa": 366}, "matt wallner": {"marcel": 0.05092, "age": 29, "seasons": 4, "cur_hr": 4, "cur_pa": 135}, "royce lewis": {"marcel": 0.04162, "age": 27, "seasons": 3, "cur_hr": 10, "cur_pa": 264}, "ryan jeffers": {"marcel": 0.03214, "age": 29, "seasons": 6, "cur_hr": 8, "cur_pa": 168}, "ryan kreidler": {"marcel": 0.01677, "age": 29, "seasons": 2, "cur_hr": 5, "cur_pa": 151}, "trevor larnach": {"marcel": 0.0324, "age": 29, "seasons": 5, "cur_hr": 7, "cur_pa": 298}, "tristan gray": {"marcel": 0.02759, "age": 30, "seasons": 1, "cur_hr": 4, "cur_pa": 182}, "victor caratini": {"marcel": 0.02924, "age": 33, "seasons": 9, "cur_hr": 7, "cur_pa": 272}, "adolis garcia": {"marcel": 0.04181, "age": 33, "seasons": 5, "cur_hr": 7, "cur_pa": 259}, "alec bohm": {"marcel": 0.02551, "age": 30, "seasons": 6, "cur_hr": 12, "cur_pa": 387}, "brandon marsh": {"marcel": 0.02799, "age": 29, "seasons": 7, "cur_hr": 15, "cur_pa": 376}, "bryan de la cruz": {"marcel": 0.03013, "age": 30, "seasons": 7, "cur_hr": 0, "cur_pa": 0}, "bryce harper": {"marcel": 0.04311, "age": 34, "seasons": 14, "cur_hr": 20, "cur_pa": 421}, "bryson stott": {"marcel": 0.02196, "age": 29, "seasons": 4, "cur_hr": 7, "cur_pa": 364}, "christian cairo": {"marcel": 0.02148, "age": 25, "seasons": 0, "cur_hr": 0, "cur_pa": 0}, "derek hill": {"marcel": 0.02315, "age": 31, "seasons": 7, "cur_hr": 4, "cur_pa": 90}, "edmundo sosa": {"marcel": 0.03277, "age": 30, "seasons": 7, "cur_hr": 5, "cur_pa": 167}, "felix reyes": {"marcel": 0.02148, "age": 25, "seasons": 0, "cur_hr": 1, "cur_pa": 38}, "gabriel rincones jr": {"marcel": 0.02148, "age": 25, "seasons": 0, "cur_hr": 2, "cur_pa": 76}, "garrett stubbs": {"marcel": 0.0147, "age": 33, "seasons": 3, "cur_hr": 0, "cur_pa": 32}, "jt realmuto": {"marcel": 0.02823, "age": 35, "seasons": 11, "cur_hr": 7, "cur_pa": 268}, "johan rojas": {"marcel": 0.01004, "age": 26, "seasons": 3, "cur_hr": 0, "cur_pa": 0}, "justin crawford": {"marcel": 0.02148, "age": 22, "seasons": 0, "cur_hr": 2, "cur_pa": 294}, "kyle schwarber": {"marcel": 0.06422, "age": 33, "seasons": 12, "cur_hr": 33, "cur_pa": 427}, "otto kemp": {"marcel": 0.03229, "age": 27, "seasons": 1, "cur_hr": 0, "cur_pa": 27}, "rafael marchan": {"marcel": 0.02454, "age": 27, "seasons": 3, "cur_hr": 2, "cur_pa": 89}, "steward berroa": {"marcel": 0.02148, "age": 27, "seasons": 0, "cur_hr": 0, "cur_pa": 7}, "trea turner": {"marcel": 0.03102, "age": 33, "seasons": 12, "cur_hr": 12, "cur_pa": 428}, "austin riley": {"marcel": 0.04145, "age": 29, "seasons": 7, "cur_hr": 12, "cur_pa": 398}, "brewer hicklen": {"marcel": 0.02148, "age": 30, "seasons": 0, "cur_hr": 0, "cur_pa": 13}, "dashawn keirsey jr": {"marcel": 0.02206, "age": 29, "seasons": 1, "cur_hr": 0, "cur_pa": 0}, "dominic smith": {"marcel": 0.02112, "age": 31, "seasons": 10, "cur_hr": 6, "cur_pa": 242}, "drake baldwin": {"marcel": 0.03966, "age": 25, "seasons": 1, "cur_hr": 18, "cur_pa": 334}, "eli white": {"marcel": 0.03043, "age": 32, "seasons": 4, "cur_hr": 5, "cur_pa": 130}, "ha-seong kim": {"marcel": 0.02481, "age": 31, "seasons": 7, "cur_hr": 0, "cur_pa": 82}, "jim jarvis": {"marcel": 0.02148, "age": 26, "seasons": 0, "cur_hr": 1, "cur_pa": 45}, "joey bart": {"marcel": 0.02312, "age": 30, "seasons": 5, "cur_hr": 2, "cur_pa": 62}, "jorge mateo": {"marcel": 0.0201, "age": 31, "seasons": 7, "cur_hr": 4, "cur_pa": 135}, "kyle farmer": {"marcel": 0.02503, "age": 36, "seasons": 8, "cur_hr": 0, "cur_pa": 16}, "matt olson": {"marcel": 0.04795, "age": 32, "seasons": 9, "cur_hr": 26, "cur_pa": 431}, "mauricio dubon": {"marcel": 0.01591, "age": 32, "seasons": 9, "cur_hr": 10, "cur_pa": 386}, "michael harris ii": {"marcel": 0.03266, "age": 25, "seasons": 4, "cur_hr": 17, "cur_pa": 369}, "mike yastrzemski": {"marcel": 0.0284, "age": 36, "seasons": 9, "cur_hr": 6, "cur_pa": 262}, "nacho alvarez jr": {"marcel": 0.01395, "age": 23, "seasons": 1, "cur_hr": 0, "cur_pa": 0}, "ozzie albies": {"marcel": 0.03053, "age": 29, "seasons": 9, "cur_hr": 14, "cur_pa": 425}, "ronald acuna jr": {"marcel": 0.04559, "age": 29, "seasons": 8, "cur_hr": 7, "cur_pa": 236}, "sean murphy": {"marcel": 0.04267, "age": 32, "seasons": 7, "cur_hr": 0, "cur_pa": 14}, "andrew benintendi": {"marcel": 0.03012, "age": 32, "seasons": 12, "cur_hr": 10, "cur_pa": 298}, "austin hays": {"marcel": 0.02941, "age": 31, "seasons": 10, "cur_hr": 1, "cur_pa": 44}, "braden montgomery": {"marcel": 0.02148, "age": 23, "seasons": 0, "cur_hr": 3, "cur_pa": 128}, "brooks baldwin": {"marcel": 0.02868, "age": 26, "seasons": 2, "cur_hr": 0, "cur_pa": 0}, "chase meidroth": {"marcel": 0.0121, "age": 25, "seasons": 1, "cur_hr": 7, "cur_pa": 399}, "colson montgomery": {"marcel": 0.06209, "age": 24, "seasons": 1, "cur_hr": 24, "cur_pa": 394}, "drew romo": {"marcel": 0.01438, "age": 25, "seasons": 1, "cur_hr": 5, "cur_pa": 123}, "edgar quero": {"marcel": 0.01472, "age": 23, "seasons": 1, "cur_hr": 2, "cur_pa": 172}, "everson pereira": {"marcel": 0.01637, "age": 25, "seasons": 2, "cur_hr": 3, "cur_pa": 77}, "junior perez": {"marcel": 0.02148, "age": 25, "seasons": 0, "cur_hr": 2, "cur_pa": 34}, "kyle teel": {"marcel": 0.02633, "age": 24, "seasons": 1, "cur_hr": 2, "cur_pa": 69}, "luisangel acuna": {"marcel": 0.00755, "age": 24, "seasons": 1, "cur_hr": 1, "cur_pa": 161}, "miguel vargas": {"marcel": 0.02666, "age": 27, "seasons": 6, "cur_hr": 21, "cur_pa": 422}, "munetaka murakami": {"marcel": 0.02148, "age": 26, "seasons": 0, "cur_hr": 20, "cur_pa": 272}, "randal grichuk": {"marcel": 0.0293, "age": 35, "seasons": 16, "cur_hr": 0, "cur_pa": 33}, "rikuu nishida": {"marcel": 0.02148, "age": 25, "seasons": 0, "cur_hr": 0, "cur_pa": 30}, "sam antonacci": {"marcel": 0.02148, "age": 23, "seasons": 0, "cur_hr": 7, "cur_pa": 317}, "tanner murray": {"marcel": 0.02148, "age": 27, "seasons": 0, "cur_hr": 1, "cur_pa": 33}, "tristan peters": {"marcel": 0.02148, "age": 26, "seasons": 0, "cur_hr": 6, "cur_pa": 286}, "agustin ramirez": {"marcel": 0.0346, "age": 25, "seasons": 1, "cur_hr": 2, "cur_pa": 129}, "brian navarreto": {"marcel": 0.02148, "age": 32, "seasons": 0, "cur_hr": 0, "cur_pa": 14}, "connor norby": {"marcel": 0.03175, "age": 26, "seasons": 3, "cur_hr": 4, "cur_pa": 233}, "deyvison de los santos": {"marcel": 0.02148, "age": 23, "seasons": 0, "cur_hr": 0, "cur_pa": 7}, "esteury ruiz": {"marcel": 0.01443, "age": 27, "seasons": 2, "cur_hr": 5, "cur_pa": 123}, "graham pauley": {"marcel": 0.02204, "age": 26, "seasons": 1, "cur_hr": 1, "cur_pa": 97}, "griffin conine": {"marcel": 0.02562, "age": 29, "seasons": 2, "cur_hr": 7, "cur_pa": 99}, "heriberto hernandez": {"marcel": 0.0312, "age": 27, "seasons": 1, "cur_hr": 13, "cur_pa": 241}, "jakob marsee": {"marcel": 0.02191, "age": 25, "seasons": 1, "cur_hr": 5, "cur_pa": 396}, "jared serna": {"marcel": 0.02148, "age": 24, "seasons": 0, "cur_hr": 0, "cur_pa": 0}, "javier sanoja": {"marcel": 0.01899, "age": 24, "seasons": 1, "cur_hr": 3, "cur_pa": 255}, "joe mack": {"marcel": 0.02148, "age": 24, "seasons": 0, "cur_hr": 7, "cur_pa": 180}, "kyle stowers": {"marcel": 0.03775, "age": 28, "seasons": 4, "cur_hr": 12, "cur_pa": 317}, "leo jimenez": {"marcel": 0.02031, "age": 25, "seasons": 1, "cur_hr": 2, "cur_pa": 133}, "liam hicks": {"marcel": 0.01683, "age": 27, "seasons": 1, "cur_hr": 13, "cur_pa": 354}, "maximo acosta": {"marcel": 0.03293, "age": 24, "seasons": 1, "cur_hr": 0, "cur_pa": 0}, "otto lopez": {"marcel": 0.0212, "age": 28, "seasons": 2, "cur_hr": 9, "cur_pa": 419}, "owen caissie": {"marcel": 0.02148, "age": 24, "seasons": 0, "cur_hr": 12, "cur_pa": 246}, "rece hinds": {"marcel": 0.04819, "age": 26, "seasons": 1, "cur_hr": 0, "cur_pa": 36}, "xavier edwards": {"marcel": 0.0058, "age": 27, "seasons": 3, "cur_hr": 6, "cur_pa": 421}, "aaron judge": {"marcel": 0.07598, "age": 34, "seasons": 10, "cur_hr": 17, "cur_pa": 261}, "ali sanchez": {"marcel": 0.01096, "age": 29, "seasons": 1, "cur_hr": 0, "cur_pa": 38}, "amed rosario": {"marcel": 0.02276, "age": 31, "seasons": 14, "cur_hr": 9, "cur_pa": 166}, "anthony volpe": {"marcel": 0.02768, "age": 25, "seasons": 3, "cur_hr": 1, "cur_pa": 164}, "austin wells": {"marcel": 0.0396, "age": 27, "seasons": 3, "cur_hr": 6, "cur_pa": 226}, "ben rice": {"marcel": 0.04436, "age": 27, "seasons": 2, "cur_hr": 29, "cur_pa": 402}, "cody bellinger": {"marcel": 0.03957, "age": 31, "seasons": 9, "cur_hr": 11, "cur_pa": 414}, "giancarlo stanton": {"marcel": 0.06174, "age": 37, "seasons": 16, "cur_hr": 3, "cur_pa": 96}, "jc escarra": {"marcel": 0.02082, "age": 31, "seasons": 1, "cur_hr": 0, "cur_pa": 92}, "jasson dominguez": {"marcel": 0.02446, "age": 23, "seasons": 2, "cur_hr": 5, "cur_pa": 152}, "jazz chisholm jr": {"marcel": 0.04662, "age": 28, "seasons": 8, "cur_hr": 14, "cur_pa": 371}, "jose caballero": {"marcel": 0.01389, "age": 30, "seasons": 5, "cur_hr": 10, "cur_pa": 306}, "max schuemann": {"marcel": 0.01418, "age": 29, "seasons": 2, "cur_hr": 2, "cur_pa": 71}, "oswaldo cabrera": {"marcel": 0.01853, "age": 27, "seasons": 4, "cur_hr": 0, "cur_pa": 11}, "paul goldschmidt": {"marcel": 0.02775, "age": 39, "seasons": 15, "cur_hr": 15, "cur_pa": 270}, "ryan mcmahon": {"marcel": 0.03331, "age": 32, "seasons": 10, "cur_hr": 9, "cur_pa": 232}, "spencer jones": {"marcel": 0.02148, "age": 25, "seasons": 0, "cur_hr": 2, "cur_pa": 82}, "trent grisham": {"marcel": 0.04354, "age": 30, "seasons": 7, "cur_hr": 11, "cur_pa": 316}, "akil baddoo": {"marcel": 0.0237, "age": 28, "seasons": 4, "cur_hr": 0, "cur_pa": 0}, "andrew vaughn": {"marcel": 0.03023, "age": 28, "seasons": 7, "cur_hr": 2, "cur_pa": 176}, "blake perkins": {"marcel": 0.017, "age": 30, "seasons": 3, "cur_hr": 1, "cur_pa": 101}, "braden shewmake": {"marcel": 0.01885, "age": 29, "seasons": 1, "cur_hr": 3, "cur_pa": 83}, "brandon lockridge": {"marcel": 0.00542, "age": 29, "seasons": 3, "cur_hr": 0, "cur_pa": 96}, "brice turang": {"marcel": 0.01948, "age": 27, "seasons": 3, "cur_hr": 14, "cur_pa": 425}, "christian yelich": {"marcel": 0.03689, "age": 35, "seasons": 13, "cur_hr": 6, "cur_pa": 290}, "cooper pratt": {"marcel": 0.02148, "age": 22, "seasons": 0, "cur_hr": 0, "cur_pa": 97}, "david hamilton": {"marcel": 0.02668, "age": 29, "seasons": 2, "cur_hr": 3, "cur_pa": 238}, "garrett mitchell": {"marcel": 0.02619, "age": 28, "seasons": 4, "cur_hr": 8, "cur_pa": 323}, "gary sanchez": {"marcel": 0.0475, "age": 34, "seasons": 11, "cur_hr": 8, "cur_pa": 181}, "jackson chourio": {"marcel": 0.0364, "age": 22, "seasons": 2, "cur_hr": 13, "cur_pa": 297}, "jake bauers": {"marcel": 0.03439, "age": 31, "seasons": 8, "cur_hr": 18, "cur_pa": 358}, "jeferson quero": {"marcel": 0.02148, "age": 24, "seasons": 0, "cur_hr": 0, "cur_pa": 2}, "joey ortiz": {"marcel": 0.01775, "age": 28, "seasons": 2, "cur_hr": 4, "cur_pa": 252}, "luis lara": {"marcel": 0.02148, "age": 22, "seasons": 0, "cur_hr": 0, "cur_pa": 27}, "sal frelick": {"marcel": 0.01424, "age": 26, "seasons": 3, "cur_hr": 4, "cur_pa": 313}, "tyler black": {"marcel": 0.01393, "age": 26, "seasons": 1, "cur_hr": 0, "cur_pa": 28}, "william contreras": {"marcel": 0.0287, "age": 29, "seasons": 5, "cur_hr": 10, "cur_pa": 396}, "adam frazier": {"marcel": 0.01532, "age": 35, "seasons": 14, "cur_hr": 1, "cur_pa": 93}, "anthony rendon": {"marcel": 0.01069, "age": 36, "seasons": 12, "cur_hr": 0, "cur_pa": 0}, "bryce teodosio": {"marcel": 0.01274, "age": 27, "seasons": 1, "cur_hr": 0, "cur_pa": 51}, "christian moore": {"marcel": 0.03318, "age": 24, "seasons": 1, "cur_hr": 0, "cur_pa": 22}, "denzer guzman": {"marcel": 0.02148, "age": 22, "seasons": 0, "cur_hr": 4, "cur_pa": 123}, "gustavo campero": {"marcel": 0.03101, "age": 29, "seasons": 1, "cur_hr": 0, "cur_pa": 0}, "jo adell": {"marcel": 0.05413, "age": 27, "seasons": 6, "cur_hr": 13, "cur_pa": 411}, "jorge soler": {"marcel": 0.03454, "age": 34, "seasons": 16, "cur_hr": 11, "cur_pa": 322}, "jose siri": {"marcel": 0.04532, "age": 31, "seasons": 5, "cur_hr": 5, "cur_pa": 100}, "josh lowe": {"marcel": 0.02926, "age": 28, "seasons": 4, "cur_hr": 8, "cur_pa": 191}, "kyren paris": {"marcel": 0.03211, "age": 25, "seasons": 2, "cur_hr": 0, "cur_pa": 0}, "logan ohoppe": {"marcel": 0.04292, "age": 26, "seasons": 3, "cur_hr": 4, "cur_pa": 239}, "logan porter": {"marcel": 0.02148, "age": 31, "seasons": 0, "cur_hr": 0, "cur_pa": 0}, "mike trout": {"marcel": 0.04778, "age": 35, "seasons": 15, "cur_hr": 18, "cur_pa": 367}, "nolan schanuel": {"marcel": 0.02107, "age": 24, "seasons": 3, "cur_hr": 6, "cur_pa": 333}, "oswald peraza": {"marcel": 0.01954, "age": 26, "seasons": 5, "cur_hr": 7, "cur_pa": 282}, "sebastian rivero": {"marcel": 0.02148, "age": 28, "seasons": 0, "cur_hr": 0, "cur_pa": 57}, "travis darnaud": {"marcel": 0.03387, "age": 37, "seasons": 13, "cur_hr": 1, "cur_pa": 40}, "tyler heineman": {"marcel": 0.00956, "age": 35, "seasons": 4, "cur_hr": 1, "cur_pa": 87}, "vaughn grissom": {"marcel": 0.01369, "age": 25, "seasons": 3, "cur_hr": 5, "cur_pa": 222}, "wade meckler": {"marcel": 0.01333, "age": 26, "seasons": 1, "cur_hr": 2, "cur_pa": 142}, "yoan moncada": {"marcel": 0.03234, "age": 31, "seasons": 8, "cur_hr": 3, "cur_pa": 130}, "zach neto": {"marcel": 0.04014, "age": 25, "seasons": 3, "cur_hr": 19, "cur_pa": 436}, "adrian del castillo": {"marcel": 0.03174, "age": 27, "seasons": 2, "cur_hr": 5, "cur_pa": 168}, "corbin carroll": {"marcel": 0.04015, "age": 26, "seasons": 4, "cur_hr": 14, "cur_pa": 410}, "gabriel moreno": {"marcel": 0.02145, "age": 26, "seasons": 4, "cur_hr": 6, "cur_pa": 288}, "geraldo perdomo": {"marcel": 0.01993, "age": 27, "seasons": 4, "cur_hr": 7, "cur_pa": 404}, "ildemaro vargas": {"marcel": 0.01258, "age": 35, "seasons": 8, "cur_hr": 7, "cur_pa": 304}, "james mccann": {"marcel": 0.03042, "age": 36, "seasons": 11, "cur_hr": 2, "cur_pa": 73}, "jordan lawlar": {"marcel": 0.01272, "age": 24, "seasons": 1, "cur_hr": 1, "cur_pa": 44}, "jorge barrosa": {"marcel": 0.01821, "age": 25, "seasons": 1, "cur_hr": 2, "cur_pa": 130}, "jose fernandez": {"marcel": 0.02148, "age": 23, "seasons": 0, "cur_hr": 3, "cur_pa": 177}, "ketel marte": {"marcel": 0.04869, "age": 33, "seasons": 11, "cur_hr": 17, "cur_pa": 419}, "lourdes gurriel jr": {"marcel": 0.03437, "age": 33, "seasons": 8, "cur_hr": 2, "cur_pa": 189}, "lujames groover": {"marcel": 0.02148, "age": 24, "seasons": 0, "cur_hr": 1, "cur_pa": 54}, "max kepler": {"marcel": 0.03428, "age": 33, "seasons": 10, "cur_hr": 1, "cur_pa": 51}, "nolan arenado": {"marcel": 0.02974, "age": 35, "seasons": 13, "cur_hr": 13, "cur_pa": 359}, "ryan waldschmidt": {"marcel": 0.02148, "age": 24, "seasons": 0, "cur_hr": 0, "cur_pa": 135}, "tim tawa": {"marcel": 0.02849, "age": 27, "seasons": 1, "cur_hr": 4, "cur_pa": 107}, "tommy troy": {"marcel": 0.02148, "age": 24, "seasons": 0, "cur_hr": 4, "cur_pa": 134}, "tyler locklear": {"marcel": 0.02426, "age": 26, "seasons": 1, "cur_hr": 0, "cur_pa": 4}, "adley rutschman": {"marcel": 0.02791, "age": 28, "seasons": 4, "cur_hr": 8, "cur_pa": 284}, "blaze alexander": {"marcel": 0.02275, "age": 27, "seasons": 2, "cur_hr": 4, "cur_pa": 246}, "christian encarnacion-strand": {"marcel": 0.03781, "age": 27, "seasons": 3, "cur_hr": 0, "cur_pa": 5}, "coby mayo": {"marcel": 0.03417, "age": 25, "seasons": 1, "cur_hr": 13, "cur_pa": 255}, "colton cowser": {"marcel": 0.04009, "age": 26, "seasons": 3, "cur_hr": 8, "cur_pa": 242}, "dylan beavers": {"marcel": 0.02656, "age": 25, "seasons": 1, "cur_hr": 2, "cur_pa": 159}, "gunnar henderson": {"marcel": 0.0397, "age": 25, "seasons": 4, "cur_hr": 17, "cur_pa": 453}, "heston kjerstad": {"marcel": 0.02652, "age": 27, "seasons": 2, "cur_hr": 0, "cur_pa": 0}, "jackson holliday": {"marcel": 0.02622, "age": 23, "seasons": 2, "cur_hr": 5, "cur_pa": 151}, "jeremiah jackson": {"marcel": 0.02571, "age": 26, "seasons": 1, "cur_hr": 7, "cur_pa": 215}, "johnathan rodriguez": {"marcel": 0.02372, "age": 27, "seasons": 1, "cur_hr": 0, "cur_pa": 11}, "jordan westburg": {"marcel": 0.0381, "age": 27, "seasons": 3, "cur_hr": 0, "cur_pa": 0}, "leody taveras": {"marcel": 0.0176, "age": 28, "seasons": 8, "cur_hr": 4, "cur_pa": 297}, "pete alonso": {"marcel": 0.05383, "age": 32, "seasons": 7, "cur_hr": 21, "cur_pa": 433}, "reed trimble": {"marcel": 0.02148, "age": 26, "seasons": 0, "cur_hr": 0, "cur_pa": 0}, "rudy martin jr": {"marcel": 0.02148, "age": 30, "seasons": 0, "cur_hr": 0, "cur_pa": 0}, "ryan mountcastle": {"marcel": 0.02661, "age": 29, "seasons": 6, "cur_hr": 0, "cur_pa": 15}, "sam huff": {"marcel": 0.0284, "age": 28, "seasons": 2, "cur_hr": 0, "cur_pa": 27}, "samuel basallo": {"marcel": 0.02939, "age": 22, "seasons": 1, "cur_hr": 16, "cur_pa": 311}, "taylor ward": {"marcel": 0.04297, "age": 33, "seasons": 7, "cur_hr": 7, "cur_pa": 453}, "tyler oneill": {"marcel": 0.04922, "age": 31, "seasons": 8, "cur_hr": 6, "cur_pa": 177}, "andruw monasterio": {"marcel": 0.01601, "age": 29, "seasons": 3, "cur_hr": 5, "cur_pa": 177}, "anthony seigler": {"marcel": 0.01257, "age": 27, "seasons": 1, "cur_hr": 2, "cur_pa": 98}, "brett harris": {"marcel": 0.01596, "age": 28, "seasons": 2, "cur_hr": 0, "cur_pa": 6}, "caleb durbin": {"marcel": 0.02209, "age": 26, "seasons": 1, "cur_hr": 9, "cur_pa": 334}, "carlos narvaez": {"marcel": 0.03159, "age": 28, "seasons": 1, "cur_hr": 3, "cur_pa": 180}, "ceddanne rafaela": {"marcel": 0.0267, "age": 26, "seasons": 3, "cur_hr": 8, "cur_pa": 385}, "connor wong": {"marcel": 0.01941, "age": 30, "seasons": 4, "cur_hr": 1, "cur_pa": 140}, "isiah kiner-falefa": {"marcel": 0.00814, "age": 31, "seasons": 11, "cur_hr": 2, "cur_pa": 132}, "jahmai jones": {"marcel": 0.02992, "age": 29, "seasons": 2, "cur_hr": 2, "cur_pa": 105}, "jarren duran": {"marcel": 0.02478, "age": 30, "seasons": 5, "cur_hr": 13, "cur_pa": 391}, "kristian campbell": {"marcel": 0.02312, "age": 24, "seasons": 1, "cur_hr": 0, "cur_pa": 0}, "marcelo mayer": {"marcel": 0.02683, "age": 24, "seasons": 1, "cur_hr": 3, "cur_pa": 228}, "masataka yoshida": {"marcel": 0.02316, "age": 33, "seasons": 3, "cur_hr": 4, "cur_pa": 210}, "mickey gasper": {"marcel": 0.01963, "age": 31, "seasons": 1, "cur_hr": 0, "cur_pa": 119}, "nate eaton": {"marcel": 0.0114, "age": 30, "seasons": 3, "cur_hr": 1, "cur_pa": 39}, "nick sogard": {"marcel": 0.00741, "age": 29, "seasons": 2, "cur_hr": 0, "cur_pa": 41}, "roman anthony": {"marcel": 0.02624, "age": 22, "seasons": 1, "cur_hr": 1, "cur_pa": 130}, "romy gonzalez": {"marcel": 0.02642, "age": 30, "seasons": 4, "cur_hr": 1, "cur_pa": 55}, "trevor story": {"marcel": 0.03214, "age": 34, "seasons": 10, "cur_hr": 3, "cur_pa": 176}, "triston casas": {"marcel": 0.044, "age": 26, "seasons": 4, "cur_hr": 0, "cur_pa": 0}, "tsung-che cheng": {"marcel": 0.02148, "age": 25, "seasons": 0, "cur_hr": 0, "cur_pa": 38}, "willson contreras": {"marcel": 0.03671, "age": 34, "seasons": 10, "cur_hr": 22, "cur_pa": 376}, "wilyer abreu": {"marcel": 0.04111, "age": 27, "seasons": 3, "cur_hr": 15, "cur_pa": 417}, "alex bregman": {"marcel": 0.0363, "age": 32, "seasons": 10, "cur_hr": 10, "cur_pa": 444}, "carson kelly": {"marcel": 0.03452, "age": 32, "seasons": 12, "cur_hr": 6, "cur_pa": 259}, "dansby swanson": {"marcel": 0.03239, "age": 32, "seasons": 10, "cur_hr": 16, "cur_pa": 367}, "ian happ": {"marcel": 0.03375, "age": 32, "seasons": 9, "cur_hr": 17, "cur_pa": 409}, "james triantos": {"marcel": 0.02148, "age": 23, "seasons": 0, "cur_hr": 0, "cur_pa": 0}, "justin dean": {"marcel": 0.02148, "age": 30, "seasons": 0, "cur_hr": 0, "cur_pa": 7}, "kevin alcantara": {"marcel": 0.02148, "age": 24, "seasons": 0, "cur_hr": 0, "cur_pa": 19}, "matt shaw": {"marcel": 0.02889, "age": 25, "seasons": 1, "cur_hr": 4, "cur_pa": 147}, "michael busch": {"marcel": 0.04558, "age": 29, "seasons": 3, "cur_hr": 12, "cur_pa": 438}, "michael conforto": {"marcel": 0.03089, "age": 33, "seasons": 10, "cur_hr": 8, "cur_pa": 165}, "miguel amaya": {"marcel": 0.027, "age": 27, "seasons": 3, "cur_hr": 3, "cur_pa": 162}, "moises ballesteros": {"marcel": 0.02589, "age": 23, "seasons": 1, "cur_hr": 6, "cur_pa": 175}, "nico hoerner": {"marcel": 0.01192, "age": 29, "seasons": 7, "cur_hr": 4, "cur_pa": 433}, "pedro ramirez": {"marcel": 0.02148, "age": 22, "seasons": 0, "cur_hr": 1, "cur_pa": 71}, "pete crow-armstrong": {"marcel": 0.03955, "age": 24, "seasons": 2, "cur_hr": 21, "cur_pa": 431}, "seiya suzuki": {"marcel": 0.03999, "age": 32, "seasons": 4, "cur_hr": 15, "cur_pa": 356}, "tyler austin": {"marcel": 0.04742, "age": 35, "seasons": 6, "cur_hr": 0, "cur_pa": 0}, "blake dunn": {"marcel": 0.0181, "age": 28, "seasons": 1, "cur_hr": 2, "cur_pa": 155}, "dane myers": {"marcel": 0.01977, "age": 30, "seasons": 3, "cur_hr": 3, "cur_pa": 146}, "edwin arroyo": {"marcel": 0.02148, "age": 23, "seasons": 0, "cur_hr": 0, "cur_pa": 114}, "elly de la cruz": {"marcel": 0.03331, "age": 24, "seasons": 3, "cur_hr": 16, "cur_pa": 354}, "eugenio suarez": {"marcel": 0.07017, "age": 35, "seasons": 14, "cur_hr": 12, "cur_pa": 279}, "hector rodriguez": {"marcel": 0.02148, "age": 22, "seasons": 0, "cur_hr": 0, "cur_pa": 0}, "ivan johnson": {"marcel": 0.02148, "age": 28, "seasons": 0, "cur_hr": 0, "cur_pa": 6}, "jj bleday": {"marcel": 0.03369, "age": 29, "seasons": 4, "cur_hr": 16, "cur_pa": 297}, "jose trevino": {"marcel": 0.02134, "age": 34, "seasons": 7, "cur_hr": 3, "cur_pa": 74}, "kebryan hayes": {"marcel": 0.00949, "age": 29, "seasons": 8, "cur_hr": 2, "cur_pa": 139}, "leo balcazar": {"marcel": 0.02148, "age": 22, "seasons": 0, "cur_hr": 0, "cur_pa": 0}, "matt mclain": {"marcel": 0.0304, "age": 27, "seasons": 2, "cur_hr": 8, "cur_pa": 309}, "nathaniel lowe": {"marcel": 0.02906, "age": 31, "seasons": 9, "cur_hr": 11, "cur_pa": 231}, "noelvi marte": {"marcel": 0.02992, "age": 25, "seasons": 3, "cur_hr": 6, "cur_pa": 141}, "sal stewart": {"marcel": 0.04687, "age": 23, "seasons": 1, "cur_hr": 20, "cur_pa": 428}, "spencer steer": {"marcel": 0.03342, "age": 29, "seasons": 4, "cur_hr": 16, "cur_pa": 371}, "tj friedl": {"marcel": 0.02675, "age": 31, "seasons": 4, "cur_hr": 3, "cur_pa": 222}, "tyler stephenson": {"marcel": 0.03289, "age": 30, "seasons": 5, "cur_hr": 8, "cur_pa": 265}, "will banfield": {"marcel": 0.02148, "age": 27, "seasons": 0, "cur_hr": 0, "cur_pa": 0}, "angel genao": {"marcel": 0.02148, "age": 22, "seasons": 0, "cur_hr": 0, "cur_pa": 0}, "angel martinez": {"marcel": 0.02227, "age": 24, "seasons": 2, "cur_hr": 11, "cur_pa": 243}, "austin hedges": {"marcel": 0.01796, "age": 34, "seasons": 12, "cur_hr": 3, "cur_pa": 147}, "bo naylor": {"marcel": 0.03526, "age": 26, "seasons": 3, "cur_hr": 2, "cur_pa": 90}, "brayan rocchio": {"marcel": 0.01552, "age": 25, "seasons": 3, "cur_hr": 8, "cur_pa": 371}, "cj kayfus": {"marcel": 0.02645, "age": 25, "seasons": 1, "cur_hr": 1, "cur_pa": 25}, "chase delauter": {"marcel": 0.02148, "age": 25, "seasons": 0, "cur_hr": 11, "cur_pa": 345}, "cooper ingle": {"marcel": 0.02148, "age": 24, "seasons": 0, "cur_hr": 0, "cur_pa": 24}, "daniel schneemann": {"marcel": 0.02601, "age": 29, "seasons": 2, "cur_hr": 6, "cur_pa": 265}, "david fry": {"marcel": 0.03745, "age": 31, "seasons": 3, "cur_hr": 6, "cur_pa": 151}, "gabriel arias": {"marcel": 0.02424, "age": 26, "seasons": 4, "cur_hr": 5, "cur_pa": 105}, "jose ramirez": {"marcel": 0.04446, "age": 34, "seasons": 12, "cur_hr": 10, "cur_pa": 314}, "juan brito": {"marcel": 0.02148, "age": 25, "seasons": 0, "cur_hr": 0, "cur_pa": 56}, "kahlil watson": {"marcel": 0.02148, "age": 23, "seasons": 0, "cur_hr": 1, "cur_pa": 89}, "kyle manzardo": {"marcel": 0.04479, "age": 26, "seasons": 2, "cur_hr": 10, "cur_pa": 319}, "patrick bailey": {"marcel": 0.01683, "age": 27, "seasons": 3, "cur_hr": 1, "cur_pa": 89}, "petey halpin": {"marcel": 0.02148, "age": 24, "seasons": 0, "cur_hr": 0, "cur_pa": 71}, "rhys hoskins": {"marcel": 0.04244, "age": 33, "seasons": 8, "cur_hr": 9, "cur_pa": 269}, "steven kwan": {"marcel": 0.01646, "age": 29, "seasons": 4, "cur_hr": 1, "cur_pa": 365}, "travis bazzana": {"marcel": 0.02148, "age": 24, "seasons": 0, "cur_hr": 8, "cur_pa": 295}, "adael amador": {"marcel": 0.0143, "age": 23, "seasons": 1, "cur_hr": 0, "cur_pa": 0}, "braxton fulford": {"marcel": 0.01439, "age": 28, "seasons": 1, "cur_hr": 1, "cur_pa": 66}, "brenton doyle": {"marcel": 0.03043, "age": 28, "seasons": 3, "cur_hr": 1, "cur_pa": 122}, "brett sullivan": {"marcel": 0.01677, "age": 32, "seasons": 1, "cur_hr": 4, "cur_pa": 137}, "chad stevens": {"marcel": 0.02148, "age": 27, "seasons": 0, "cur_hr": 0, "cur_pa": 34}, "cole carrigg": {"marcel": 0.02148, "age": 24, "seasons": 0, "cur_hr": 4, "cur_pa": 125}, "edouard julien": {"marcel": 0.02713, "age": 27, "seasons": 3, "cur_hr": 3, "cur_pa": 255}, "ezequiel tovar": {"marcel": 0.02976, "age": 25, "seasons": 3, "cur_hr": 8, "cur_pa": 348}, "hunter goodman": {"marcel": 0.04967, "age": 27, "seasons": 3, "cur_hr": 30, "cur_pa": 384}, "jake mccarthy": {"marcel": 0.01503, "age": 29, "seasons": 5, "cur_hr": 10, "cur_pa": 320}, "jordan beck": {"marcel": 0.02521, "age": 25, "seasons": 2, "cur_hr": 1, "cur_pa": 88}, "kris bryant": {"marcel": 0.02371, "age": 34, "seasons": 12, "cur_hr": 0, "cur_pa": 0}, "kyle karros": {"marcel": 0.01267, "age": 24, "seasons": 1, "cur_hr": 9, "cur_pa": 331}, "mickey moniak": {"marcel": 0.04259, "age": 28, "seasons": 6, "cur_hr": 15, "cur_pa": 239}, "ryan ritter": {"marcel": 0.01044, "age": 26, "seasons": 1, "cur_hr": 0, "cur_pa": 7}, "sterlin thompson": {"marcel": 0.02148, "age": 25, "seasons": 0, "cur_hr": 2, "cur_pa": 77}, "tj rumfield": {"marcel": 0.02148, "age": 26, "seasons": 0, "cur_hr": 13, "cur_pa": 397}, "troy johnston": {"marcel": 0.02782, "age": 29, "seasons": 1, "cur_hr": 3, "cur_pa": 326}, "tyler freeman": {"marcel": 0.01301, "age": 27, "seasons": 4, "cur_hr": 3, "cur_pa": 259}, "willi castro": {"marcel": 0.02438, "age": 29, "seasons": 9, "cur_hr": 9, "cur_pa": 332}, "zac veen": {"marcel": 0.02148, "age": 25, "seasons": 0, "cur_hr": 0, "cur_pa": 0}, "ben malgeri": {"marcel": 0.02148, "age": 26, "seasons": 0, "cur_hr": 0, "cur_pa": 31}, "colt keith": {"marcel": 0.02587, "age": 25, "seasons": 2, "cur_hr": 8, "cur_pa": 280}, "dillon dingler": {"marcel": 0.02514, "age": 28, "seasons": 2, "cur_hr": 19, "cur_pa": 374}, "eduardo valencia": {"marcel": 0.02148, "age": 26, "seasons": 0, "cur_hr": 2, "cur_pa": 13}, "gage workman": {"marcel": 0.02148, "age": 27, "seasons": 0, "cur_hr": 2, "cur_pa": 38}, "gleyber torres": {"marcel": 0.02713, "age": 30, "seasons": 8, "cur_hr": 4, "cur_pa": 190}, "hao-yu lee": {"marcel": 0.02148, "age": 23, "seasons": 0, "cur_hr": 4, "cur_pa": 165}, "jace jung": {"marcel": 0.00878, "age": 26, "seasons": 2, "cur_hr": 0, "cur_pa": 8}, "jake rogers": {"marcel": 0.03552, "age": 31, "seasons": 5, "cur_hr": 3, "cur_pa": 103}, "james outman": {"marcel": 0.03269, "age": 29, "seasons": 4, "cur_hr": 0, "cur_pa": 70}, "javier baez": {"marcel": 0.02189, "age": 34, "seasons": 14, "cur_hr": 2, "cur_pa": 82}, "kerry carpenter": {"marcel": 0.05124, "age": 29, "seasons": 4, "cur_hr": 13, "cur_pa": 241}, "kevin mcgonigle": {"marcel": 0.02148, "age": 22, "seasons": 0, "cur_hr": 9, "cur_pa": 426}, "matt vierling": {"marcel": 0.02255, "age": 30, "seasons": 5, "cur_hr": 5, "cur_pa": 272}, "parker meadows": {"marcel": 0.02408, "age": 27, "seasons": 3, "cur_hr": 0, "cur_pa": 39}, "riley greene": {"marcel": 0.04449, "age": 26, "seasons": 4, "cur_hr": 14, "cur_pa": 412}, "spencer torkelson": {"marcel": 0.04157, "age": 27, "seasons": 4, "cur_hr": 18, "cur_pa": 383}, "thayron liranzo": {"marcel": 0.02148, "age": 23, "seasons": 0, "cur_hr": 0, "cur_pa": 0}, "trei cruz": {"marcel": 0.02148, "age": 28, "seasons": 0, "cur_hr": 0, "cur_pa": 5}, "trey sweeney": {"marcel": 0.02217, "age": 26, "seasons": 2, "cur_hr": 0, "cur_pa": 0}, "wenceel perez": {"marcel": 0.02755, "age": 27, "seasons": 2, "cur_hr": 7, "cur_pa": 175}, "zach mckinstry": {"marcel": 0.01909, "age": 31, "seasons": 6, "cur_hr": 4, "cur_pa": 256}, "brice matthews": {"marcel": 0.02148, "age": 24, "seasons": 0, "cur_hr": 7, "cur_pa": 226}, "cam smith": {"marcel": 0.01948, "age": 23, "seasons": 1, "cur_hr": 12, "cur_pa": 374}, "carlos correa": {"marcel": 0.02177, "age": 32, "seasons": 13, "cur_hr": 3, "cur_pa": 141}, "christian vazquez": {"marcel": 0.01794, "age": 36, "seasons": 13, "cur_hr": 5, "cur_pa": 194}, "christian walker": {"marcel": 0.04369, "age": 35, "seasons": 8, "cur_hr": 20, "cur_pa": 406}, "collin price": {"marcel": 0.02148, "age": 27, "seasons": 0, "cur_hr": 0, "cur_pa": 13}, "isaac paredes": {"marcel": 0.03712, "age": 27, "seasons": 8, "cur_hr": 12, "cur_pa": 398}, "jake meyers": {"marcel": 0.01957, "age": 30, "seasons": 5, "cur_hr": 3, "cur_pa": 148}, "jeremy pena": {"marcel": 0.0241, "age": 29, "seasons": 4, "cur_hr": 6, "cur_pa": 223}, "joey loperfido": {"marcel": 0.02364, "age": 27, "seasons": 4, "cur_hr": 1, "cur_pa": 120}, "jose altuve": {"marcel": 0.03458, "age": 36, "seasons": 15, "cur_hr": 12, "cur_pa": 330}, "lamonte wade jr": {"marcel": 0.01026, "age": 32, "seasons": 8, "cur_hr": 2, "cur_pa": 46}, "lucas spence": {"marcel": 0.02148, "age": 23, "seasons": 0, "cur_hr": 0, "cur_pa": 12}, "nick allen": {"marcel": 0.0064, "age": 28, "seasons": 4, "cur_hr": 1, "cur_pa": 103}, "raynel delgado": {"marcel": 0.02148, "age": 26, "seasons": 0, "cur_hr": 1, "cur_pa": 36}, "shay whitcomb": {"marcel": 0.02148, "age": 28, "seasons": 0, "cur_hr": 2, "cur_pa": 24}, "taylor trammell": {"marcel": 0.02882, "age": 29, "seasons": 4, "cur_hr": 3, "cur_pa": 125}, "yainer diaz": {"marcel": 0.0355, "age": 28, "seasons": 3, "cur_hr": 6, "cur_pa": 183}, "yordan alvarez": {"marcel": 0.0502, "age": 29, "seasons": 6, "cur_hr": 31, "cur_pa": 434}, "zach cole": {"marcel": 0.04118, "age": 26, "seasons": 1, "cur_hr": 3, "cur_pa": 53}, "zach dezenzo": {"marcel": 0.02244, "age": 26, "seasons": 2, "cur_hr": 1, "cur_pa": 69}, "bobby witt jr": {"marcel": 0.03973, "age": 26, "seasons": 4, "cur_hr": 13, "cur_pa": 412}, "carter jensen": {"marcel": 0.03156, "age": 23, "seasons": 1, "cur_hr": 13, "cur_pa": 360}, "isaac collins": {"marcel": 0.02061, "age": 29, "seasons": 1, "cur_hr": 5, "cur_pa": 327}, "jac caglianone": {"marcel": 0.02855, "age": 23, "seasons": 1, "cur_hr": 16, "cur_pa": 361}, "john rave": {"marcel": 0.02236, "age": 29, "seasons": 1, "cur_hr": 1, "cur_pa": 21}, "jonathan india": {"marcel": 0.02227, "age": 30, "seasons": 5, "cur_hr": 2, "cur_pa": 58}, "josh rojas": {"marcel": 0.01251, "age": 32, "seasons": 9, "cur_hr": 1, "cur_pa": 40}, "kameron misner": {"marcel": 0.02268, "age": 28, "seasons": 1, "cur_hr": 0, "cur_pa": 44}, "kyle isbel": {"marcel": 0.01487, "age": 29, "seasons": 5, "cur_hr": 3, "cur_pa": 183}, "lane thomas": {"marcel": 0.02673, "age": 31, "seasons": 9, "cur_hr": 9, "cur_pa": 282}, "luke maile": {"marcel": 0.02064, "age": 35, "seasons": 8, "cur_hr": 1, "cur_pa": 11}, "maikel garcia": {"marcel": 0.01683, "age": 26, "seasons": 3, "cur_hr": 3, "cur_pa": 294}, "matthew lugo": {"marcel": 0.03703, "age": 25, "seasons": 1, "cur_hr": 0, "cur_pa": 0}, "michael massey": {"marcel": 0.02732, "age": 28, "seasons": 4, "cur_hr": 7, "cur_pa": 256}, "nick loftin": {"marcel": 0.0148, "age": 28, "seasons": 3, "cur_hr": 4, "cur_pa": 217}, "salvador perez": {"marcel": 0.0413, "age": 36, "seasons": 14, "cur_hr": 12, "cur_pa": 387}, "starling marte": {"marcel": 0.02066, "age": 38, "seasons": 18, "cur_hr": 1, "cur_pa": 125}, "tyler tolbert": {"marcel": 0.02017, "age": 28, "seasons": 1, "cur_hr": 2, "cur_pa": 64}, "vinnie pasquantino": {"marcel": 0.03983, "age": 29, "seasons": 4, "cur_hr": 6, "cur_pa": 308}, "alek thomas": {"marcel": 0.0216, "age": 26, "seasons": 4, "cur_hr": 2, "cur_pa": 100}, "alex call": {"marcel": 0.01595, "age": 32, "seasons": 7, "cur_hr": 1, "cur_pa": 135}, "alex freeland": {"marcel": 0.02156, "age": 25, "seasons": 1, "cur_hr": 3, "cur_pa": 220}, "andy pages": {"marcel": 0.03745, "age": 26, "seasons": 2, "cur_hr": 17, "cur_pa": 424}, "dalton rushing": {"marcel": 0.02469, "age": 25, "seasons": 1, "cur_hr": 10, "cur_pa": 214}, "eliezer alfonzo": {"marcel": 0.02148, "age": 27, "seasons": 0, "cur_hr": 0, "cur_pa": 11}, "enrique hernandez": {"marcel": 0.029, "age": 35, "seasons": 15, "cur_hr": 1, "cur_pa": 4}, "freddie freeman": {"marcel": 0.03581, "age": 37, "seasons": 15, "cur_hr": 15, "cur_pa": 421}, "hyeseong kim": {"marcel": 0.0193, "age": 27, "seasons": 1, "cur_hr": 1, "cur_pa": 131}, "kyle tucker": {"marcel": 0.04402, "age": 29, "seasons": 8, "cur_hr": 7, "cur_pa": 394}, "miguel rojas": {"marcel": 0.01751, "age": 37, "seasons": 12, "cur_hr": 3, "cur_pa": 159}, "mookie betts": {"marcel": 0.03781, "age": 34, "seasons": 12, "cur_hr": 11, "cur_pa": 272}, "ryan ward": {"marcel": 0.02148, "age": 28, "seasons": 0, "cur_hr": 3, "cur_pa": 60}, "shohei ohtani": {"marcel": 0.07145, "age": 32, "seasons": 8, "cur_hr": 22, "cur_pa": 419}, "teoscar hernandez": {"marcel": 0.04357, "age": 34, "seasons": 11, "cur_hr": 8, "cur_pa": 261}, "tommy edman": {"marcel": 0.03033, "age": 31, "seasons": 7, "cur_hr": 2, "cur_pa": 88}, "will smith": {"marcel": 0.03573, "age": 31, "seasons": 7, "cur_hr": 6, "cur_pa": 201}, "abimelec ortiz": {"marcel": 0.02148, "age": 24, "seasons": 0, "cur_hr": 0, "cur_pa": 2}, "andres chaparro": {"marcel": 0.02312, "age": 27, "seasons": 2, "cur_hr": 3, "cur_pa": 75}, "brady house": {"marcel": 0.01703, "age": 23, "seasons": 1, "cur_hr": 7, "cur_pa": 177}, "cj abrams": {"marcel": 0.03091, "age": 26, "seasons": 6, "cur_hr": 21, "cur_pa": 409}, "christian franklin": {"marcel": 0.02148, "age": 27, "seasons": 0, "cur_hr": 0, "cur_pa": 0}, "curtis mead": {"marcel": 0.01386, "age": 26, "seasons": 5, "cur_hr": 17, "cur_pa": 309}, "daylen lile": {"marcel": 0.02546, "age": 24, "seasons": 1, "cur_hr": 11, "cur_pa": 417}, "drew millas": {"marcel": 0.01411, "age": 28, "seasons": 2, "cur_hr": 2, "cur_pa": 152}, "dylan crews": {"marcel": 0.02847, "age": 24, "seasons": 2, "cur_hr": 7, "cur_pa": 204}, "harry ford": {"marcel": 0.02148, "age": 23, "seasons": 0, "cur_hr": 1, "cur_pa": 10}, "jacob young": {"marcel": 0.00671, "age": 27, "seasons": 3, "cur_hr": 8, "cur_pa": 298}, "james wood": {"marcel": 0.03939, "age": 24, "seasons": 2, "cur_hr": 28, "cur_pa": 469}, "joey wiemer": {"marcel": 0.03256, "age": 27, "seasons": 2, "cur_hr": 3, "cur_pa": 83}, "jorbit vivas": {"marcel": 0.01942, "age": 25, "seasons": 1, "cur_hr": 3, "cur_pa": 214}, "jose tena": {"marcel": 0.0126, "age": 25, "seasons": 3, "cur_hr": 5, "cur_pa": 191}, "keibert ruiz": {"marcel": 0.02339, "age": 28, "seasons": 6, "cur_hr": 7, "cur_pa": 216}, "luis garcia jr": {"marcel": 0.02898, "age": 26, "seasons": 6, "cur_hr": 20, "cur_pa": 324}, "nasim nunez": {"marcel": 0.0247, "age": 26, "seasons": 2, "cur_hr": 1, "cur_pa": 318}, "aj ewing": {"marcel": 0.02148, "age": 22, "seasons": 0, "cur_hr": 7, "cur_pa": 236}, "bo bichette": {"marcel": 0.02626, "age": 28, "seasons": 7, "cur_hr": 10, "cur_pa": 427}, "brett baty": {"marcel": 0.03247, "age": 27, "seasons": 3, "cur_hr": 5, "cur_pa": 337}, "carson benge": {"marcel": 0.02148, "age": 23, "seasons": 0, "cur_hr": 11, "cur_pa": 399}, "eric wagaman": {"marcel": 0.01893, "age": 29, "seasons": 2, "cur_hr": 2, "cur_pa": 42}, "francisco alvarez": {"marcel": 0.04235, "age": 25, "seasons": 3, "cur_hr": 11, "cur_pa": 240}, "francisco lindor": {"marcel": 0.04324, "age": 33, "seasons": 11, "cur_hr": 6, "cur_pa": 184}, "hayden senger": {"marcel": 0.01207, "age": 29, "seasons": 1, "cur_hr": 1, "cur_pa": 17}, "jared young": {"marcel": 0.02148, "age": 31, "seasons": 0, "cur_hr": 6, "cur_pa": 163}, "jorge polanco": {"marcel": 0.04074, "age": 33, "seasons": 10, "cur_hr": 1, "cur_pa": 83}, "juan soto": {"marcel": 0.05536, "age": 28, "seasons": 10, "cur_hr": 21, "cur_pa": 348}, "luis robert jr": {"marcel": 0.04119, "age": 29, "seasons": 6, "cur_hr": 2, "cur_pa": 98}, "luis torrens": {"marcel": 0.01923, "age": 30, "seasons": 7, "cur_hr": 2, "cur_pa": 183}, "mj melendez": {"marcel": 0.03017, "age": 28, "seasons": 4, "cur_hr": 4, "cur_pa": 144}, "marcus semien": {"marcel": 0.03136, "age": 36, "seasons": 13, "cur_hr": 9, "cur_pa": 327}, "mark vientos": {"marcel": 0.04415, "age": 27, "seasons": 3, "cur_hr": 11, "cur_pa": 254}, "nick morabito": {"marcel": 0.02148, "age": 23, "seasons": 0, "cur_hr": 0, "cur_pa": 12}, "ronny mauricio": {"marcel": 0.02705, "age": 25, "seasons": 2, "cur_hr": 1, "cur_pa": 50}, "tyrone taylor": {"marcel": 0.01802, "age": 32, "seasons": 5, "cur_hr": 7, "cur_pa": 136}}}